gif.py
pygif-0.3.dist-info/LICENSE
pygif-0.3.dist-info/METADATA
pygif-0.3.dist-info/WHEEL
pygif-0.3.dist-info/top_level.txt
pygif-0.3.dist-info/RECORD
