Metadata-Version: 2.1
Name: pygif
Version: 0.3
Summary: Pure Python GIF image encoder/decoder
Home-page: https://github.com/robert-ancell/pygif
Author: Robert Ancell
Author-email: robert.ancell@ubuntu.com
License: LGPL-3
Platform: UNKNOWN
Classifier: Topic :: Multimedia :: Graphics
Classifier: Topic :: Software Development :: Libraries :: Python Modules
Classifier: Programming Language :: Python
Classifier: Programming Language :: Python :: 3
Classifier: License :: OSI Approved :: GNU Lesser General Public License v3 (LGPLv3)
Classifier: Operating System :: OS Independent
License-File: LICENSE
